{"title": "All Arrest by Offense", "keys": ["Aggravated Assault", "All Other Offenses (Except Traffic)", "Arson", "Burglary", "Curfew and Loitering Law Violations", "Disorderly Conduct", "Driving Under the Influence", "Drug Abuse Violations - Grand Total", "Drunkenness", "Embezzlement", "Forgery and Counterfeiting", "Fraud", "Gambling - Total", "Human Trafficking - Commercial Sex Acts", "Human Trafficking - Involuntary Servitude", "Larceny - Theft", "Liquor Laws", "Manslaughter by Negligence", "Motor Vehicle Theft", "Murder and Nonnegligent Manslaughter", "Offenses Against the Family and Children", "Prostitution and Commercialized Vice", "Rape", "Robbery", "Sex Offenses (Except Rape, and Prostitution and Commercialized Vice)", "Simple Assault", "Stolen Property: Buying, Receiving, Possessing", "Suspicion", "Vagrancy", "Vandalism", "Weapons: Carrying, Possessing, Etc."], "data": [{"data_year": 2008, "Aggravated Assault": 107, "All Other Offenses (Except Traffic)": 1617, "Arson": 4, "Burglary": 91, "Curfew and Loitering Law Violations": 6, "Disorderly Conduct": 90, "Driving Under the Influence": 94, "Drug Abuse Violations - Grand Total": 340, "Drunkenness": 112, "Embezzlement": 13, "Forgery and Counterfeiting": 13, "Fraud": 56, "Gambling - Total": 0, "Human Trafficking - Commercial Sex Acts": 0, "Human Trafficking - Involuntary Servitude": 0, "Larceny - Theft": 212, "Liquor Laws": 27, "Manslaughter by Negligence": 0, "Motor Vehicle Theft": 1, "Murder and Nonnegligent Manslaughter": 13, "Offenses Against the Family and Children": 38, "Prostitution and Commercialized Vice": 12, "Rape": 6, "Robbery": 74, "Simple Assault": 638, "Stolen Property: Buying, Receiving, Possessing": 27, "Suspicion": 0, "Vagrancy": 0, "Vandalism": 91, "Weapons: Carrying, Possessing, Etc.": 75, "Sex Offenses (Except Rape, and Prostitution and Commercialized Vice)": 12}, {"data_year": 2009, "Aggravated Assault": 117, "All Other Offenses (Except Traffic)": 1349, "Arson": 2, "Burglary": 57, "Curfew and Loitering Law Violations": 1, "Disorderly Conduct": 80, "Driving Under the Influence": 97, "Drug Abuse Violations - Grand Total": 387, "Drunkenness": 89, "Embezzlement": 11, "Forgery and Counterfeiting": 30, "Fraud": 51, "Gambling - Total": 0, "Human Trafficking - Commercial Sex Acts": 0, "Human Trafficking - Involuntary Servitude": 0, "Larceny - Theft": 214, "Liquor Laws": 40, "Manslaughter by Negligence": 2, "Motor Vehicle Theft": 0, "Murder and Nonnegligent Manslaughter": 7, "Offenses Against the Family and Children": 28, "Prostitution and Commercialized Vice": 7, "Rape": 3, "Robbery": 56, "Simple Assault": 577, "Stolen Property: Buying, Receiving, Possessing": 32, "Suspicion": 0, "Vagrancy": 0, "Vandalism": 68, "Weapons: Carrying, Possessing, Etc.": 84, "Sex Offenses (Except Rape, and Prostitution and Commercialized Vice)": 11}, {"data_year": 2010, "Aggravated Assault": 79, "All Other Offenses (Except Traffic)": 1135, "Arson": 3, "Burglary": 69, "Curfew and Loitering Law Violations": 1, "Disorderly Conduct": 48, "Driving Under the Influence": 70, "Drug Abuse Violations - Grand Total": 320, "Drunkenness": 50, "Embezzlement": 5, "Forgery and Counterfeiting": 16, "Fraud": 50, "Gambling - Total": 0, "Human Trafficking - Commercial Sex Acts": 0, "Human Trafficking - Involuntary Servitude": 0, "Larceny - Theft": 164, "Liquor Laws": 53, "Manslaughter by Negligence": 0, "Motor Vehicle Theft": 0, "Murder and Nonnegligent Manslaughter": 9, "Offenses Against the Family and Children": 38, "Prostitution and Commercialized Vice": 4, "Rape": 5, "Robbery": 32, "Simple Assault": 520, "Stolen Property: Buying, Receiving, Possessing": 14, "Suspicion": 0, "Vagrancy": 0, "Vandalism": 72, "Weapons: Carrying, Possessing, Etc.": 46, "Sex Offenses (Except Rape, and Prostitution and Commercialized Vice)": 9}, {"data_year": 2011, "Aggravated Assault": 66, "All Other Offenses (Except Traffic)": 1476, "Arson": 3, "Burglary": 67, "Curfew and Loitering Law Violations": 13, "Disorderly Conduct": 93, "Driving Under the Influence": 111, "Drug Abuse Violations - Grand Total": 536, "Drunkenness": 63, "Embezzlement": 8, "Forgery and Counterfeiting": 30, "Fraud": 38, "Gambling - Total": 0, "Human Trafficking - Commercial Sex Acts": 0, "Human Trafficking - Involuntary Servitude": 0, "Larceny - Theft": 200, "Liquor Laws": 111, "Manslaughter by Negligence": 0, "Motor Vehicle Theft": 0, "Murder and Nonnegligent Manslaughter": 8, "Offenses Against the Family and Children": 42, "Prostitution and Commercialized Vice": 4, "Rape": 9, "Robbery": 26, "Simple Assault": 455, "Stolen Property: Buying, Receiving, Possessing": 25, "Suspicion": 0, "Vagrancy": 0, "Vandalism": 54, "Weapons: Carrying, Possessing, Etc.": 58, "Sex Offenses (Except Rape, and Prostitution and Commercialized Vice)": 14}, {"data_year": 2012, "Aggravated Assault": 85, "All Other Offenses (Except Traffic)": 1447, "Arson": 3, "Burglary": 50, "Curfew and Loitering Law Violations": 2, "Disorderly Conduct": 96, "Driving Under the Influence": 124, "Drug Abuse Violations - Grand Total": 641, "Drunkenness": 22, "Embezzlement": 16, "Forgery and Counterfeiting": 23, "Fraud": 25, "Gambling - Total": 0, "Human Trafficking - Commercial Sex Acts": 0, "Human Trafficking - Involuntary Servitude": 0, "Larceny - Theft": 199, "Liquor Laws": 74, "Manslaughter by Negligence": 0, "Motor Vehicle Theft": 0, "Murder and Nonnegligent Manslaughter": 9, "Offenses Against the Family and Children": 59, "Prostitution and Commercialized Vice": 2, "Rape": 7, "Robbery": 30, "Simple Assault": 464, "Stolen Property: Buying, Receiving, Possessing": 21, "Suspicion": 0, "Vagrancy": 0, "Vandalism": 60, "Weapons: Carrying, Possessing, Etc.": 62, "Sex Offenses (Except Rape, and Prostitution and Commercialized Vice)": 12}, {"data_year": 2013, "Aggravated Assault": 77, "All Other Offenses (Except Traffic)": 1177, "Arson": 0, "Burglary": 44, "Curfew and Loitering Law Violations": 2, "Disorderly Conduct": 76, "Driving Under the Influence": 92, "Drug Abuse Violations - Grand Total": 391, "Drunkenness": 21, "Embezzlement": 11, "Forgery and Counterfeiting": 25, "Fraud": 20, "Gambling - Total": 0, "Human Trafficking - Commercial Sex Acts": 0, "Human Trafficking - Involuntary Servitude": 0, "Larceny - Theft": 188, "Liquor Laws": 48, "Manslaughter by Negligence": 0, "Motor Vehicle Theft": 0, "Murder and Nonnegligent Manslaughter": 14, "Offenses Against the Family and Children": 71, "Prostitution and Commercialized Vice": 0, "Rape": 7, "Robbery": 25, "Simple Assault": 412, "Stolen Property: Buying, Receiving, Possessing": 3, "Suspicion": 0, "Vagrancy": 3, "Vandalism": 68, "Weapons: Carrying, Possessing, Etc.": 55, "Sex Offenses (Except Rape, and Prostitution and Commercialized Vice)": 5}, {"data_year": 2014, "Aggravated Assault": 69, "All Other Offenses (Except Traffic)": 938, "Arson": 1, "Burglary": 45, "Curfew and Loitering Law Violations": 6, "Disorderly Conduct": 78, "Driving Under the Influence": 90, "Drug Abuse Violations - Grand Total": 317, "Drunkenness": 23, "Embezzlement": 13, "Forgery and Counterfeiting": 9, "Fraud": 24, "Gambling - Total": 0, "Human Trafficking - Commercial Sex Acts": 0, "Human Trafficking - Involuntary Servitude": 0, "Larceny - Theft": 121, "Liquor Laws": 21, "Manslaughter by Negligence": 0, "Motor Vehicle Theft": 0, "Murder and Nonnegligent Manslaughter": 7, "Offenses Against the Family and Children": 58, "Prostitution and Commercialized Vice": 5, "Rape": 7, "Robbery": 37, "Simple Assault": 373, "Stolen Property: Buying, Receiving, Possessing": 11, "Suspicion": 0, "Vagrancy": 22, "Vandalism": 58, "Weapons: Carrying, Possessing, Etc.": 50, "Sex Offenses (Except Rape, and Prostitution and Commercialized Vice)": 6}, {"data_year": 2015, "Aggravated Assault": 67, "All Other Offenses (Except Traffic)": 715, "Arson": 4, "Burglary": 33, "Curfew and Loitering Law Violations": 14, "Disorderly Conduct": 47, "Driving Under the Influence": 75, "Drug Abuse Violations - Grand Total": 191, "Drunkenness": 20, "Embezzlement": 11, "Forgery and Counterfeiting": 12, "Fraud": 26, "Gambling - Total": 0, "Human Trafficking - Commercial Sex Acts": 0, "Human Trafficking - Involuntary Servitude": 0, "Larceny - Theft": 141, "Liquor Laws": 16, "Manslaughter by Negligence": 0, "Motor Vehicle Theft": 0, "Murder and Nonnegligent Manslaughter": 17, "Offenses Against the Family and Children": 50, "Prostitution and Commercialized Vice": 0, "Rape": 10, "Robbery": 23, "Simple Assault": 351, "Stolen Property: Buying, Receiving, Possessing": 6, "Suspicion": 0, "Vagrancy": 22, "Vandalism": 56, "Weapons: Carrying, Possessing, Etc.": 65, "Sex Offenses (Except Rape, and Prostitution and Commercialized Vice)": 6}, {"data_year": 2016, "Aggravated Assault": 64, "All Other Offenses (Except Traffic)": 752, "Arson": 0, "Burglary": 30, "Curfew and Loitering Law Violations": 4, "Disorderly Conduct": 40, "Driving Under the Influence": 61, "Drug Abuse Violations - Grand Total": 235, "Drunkenness": 8, "Embezzlement": 12, "Forgery and Counterfeiting": 11, "Fraud": 18, "Gambling - Total": 1, "Human Trafficking - Commercial Sex Acts": 0, "Human Trafficking - Involuntary Servitude": 0, "Larceny - Theft": 133, "Liquor Laws": 7, "Manslaughter by Negligence": 0, "Motor Vehicle Theft": 0, "Murder and Nonnegligent Manslaughter": 7, "Offenses Against the Family and Children": 34, "Prostitution and Commercialized Vice": 3, "Rape": 10, "Robbery": 23, "Simple Assault": 327, "Stolen Property: Buying, Receiving, Possessing": 6, "Suspicion": 0, "Vagrancy": 17, "Vandalism": 43, "Weapons: Carrying, Possessing, Etc.": 64, "Sex Offenses (Except Rape, and Prostitution and Commercialized Vice)": 6}, {"data_year": 2017, "Aggravated Assault": 87, "All Other Offenses (Except Traffic)": 933, "Arson": 3, "Burglary": 20, "Curfew and Loitering Law Violations": 11, "Disorderly Conduct": 39, "Driving Under the Influence": 60, "Drug Abuse Violations - Grand Total": 316, "Drunkenness": 59, "Embezzlement": 12, "Forgery and Counterfeiting": 15, "Fraud": 41, "Gambling - Total": 1, "Human Trafficking - Commercial Sex Acts": 0, "Human Trafficking - Involuntary Servitude": 0, "Larceny - Theft": 139, "Liquor Laws": 20, "Manslaughter by Negligence": 0, "Motor Vehicle Theft": 0, "Murder and Nonnegligent Manslaughter": 8, "Offenses Against the Family and Children": 28, "Prostitution and Commercialized Vice": 3, "Rape": 5, "Robbery": 31, "Simple Assault": 308, "Stolen Property: Buying, Receiving, Possessing": 13, "Suspicion": 0, "Vagrancy": 15, "Vandalism": 62, "Weapons: Carrying, Possessing, Etc.": 73, "Sex Offenses (Except Rape, and Prostitution and Commercialized Vice)": 1}, {"data_year": 2018, "Aggravated Assault": 94, "All Other Offenses (Except Traffic)": 1345, "Arson": 4, "Burglary": 24, "Curfew and Loitering Law Violations": 2, "Disorderly Conduct": 40, "Driving Under the Influence": 78, "Drug Abuse Violations - Grand Total": 525, "Drunkenness": 165, "Embezzlement": 19, "Forgery and Counterfeiting": 10, "Fraud": 39, "Gambling - Total": 0, "Human Trafficking - Commercial Sex Acts": 0, "Human Trafficking - Involuntary Servitude": 0, "Larceny - Theft": 155, "Liquor Laws": 21, "Manslaughter by Negligence": 1, "Motor Vehicle Theft": 0, "Murder and Nonnegligent Manslaughter": 12, "Offenses Against the Family and Children": 28, "Prostitution and Commercialized Vice": 0, "Rape": 2, "Robbery": 15, "Simple Assault": 369, "Stolen Property: Buying, Receiving, Possessing": 15, "Suspicion": 0, "Vagrancy": 14, "Vandalism": 66, "Weapons: Carrying, Possessing, Etc.": 98, "Sex Offenses (Except Rape, and Prostitution and Commercialized Vice)": 5}, {"data_year": 2019, "Aggravated Assault": 88, "All Other Offenses (Except Traffic)": 1127, "Arson": 1, "Burglary": 28, "Curfew and Loitering Law Violations": 0, "Disorderly Conduct": 44, "Driving Under the Influence": 86, "Drug Abuse Violations - Grand Total": 544, "Drunkenness": 93, "Embezzlement": 11, "Forgery and Counterfeiting": 6, "Fraud": 15, "Gambling - Total": 0, "Human Trafficking - Commercial Sex Acts": 0, "Human Trafficking - Involuntary Servitude": 0, "Larceny - Theft": 122, "Liquor Laws": 25, "Manslaughter by Negligence": 0, "Motor Vehicle Theft": 0, "Murder and Nonnegligent Manslaughter": 9, "Offenses Against the Family and Children": 24, "Prostitution and Commercialized Vice": 0, "Rape": 3, "Robbery": 19, "Simple Assault": 305, "Stolen Property: Buying, Receiving, Possessing": 20, "Suspicion": 0, "Vagrancy": 5, "Vandalism": 58, "Weapons: Carrying, Possessing, Etc.": 85, "Sex Offenses (Except Rape, and Prostitution and Commercialized Vice)": 5}, {"data_year": 2020, "Aggravated Assault": 65, "All Other Offenses (Except Traffic)": 693, "Arson": 2, "Burglary": 13, "Curfew and Loitering Law Violations": 0, "Disorderly Conduct": 40, "Driving Under the Influence": 59, "Drug Abuse Violations - Grand Total": 200, "Drunkenness": 49, "Embezzlement": 2, "Forgery and Counterfeiting": 4, "Fraud": 10, "Gambling - Total": 0, "Human Trafficking - Commercial Sex Acts": 0, "Human Trafficking - Involuntary Servitude": 0, "Larceny - Theft": 99, "Liquor Laws": 10, "Manslaughter by Negligence": 1, "Motor Vehicle Theft": 0, "Murder and Nonnegligent Manslaughter": 7, "Offenses Against the Family and Children": 19, "Prostitution and Commercialized Vice": 0, "Rape": 1, "Robbery": 12, "Simple Assault": 160, "Stolen Property: Buying, Receiving, Possessing": 8, "Suspicion": 0, "Vagrancy": 5, "Vandalism": 32, "Weapons: Carrying, Possessing, Etc.": 107, "Sex Offenses (Except Rape, and Prostitution and Commercialized Vice)": 6}, {"data_year": 2021, "Aggravated Assault": 71, "All Other Offenses (Except Traffic)": 322, "Arson": 2, "Burglary": 5, "Curfew and Loitering Law Violations": 0, "Disorderly Conduct": 38, "Driving Under the Influence": 41, "Drug Abuse Violations - Grand Total": 38, "Drunkenness": 0, "Embezzlement": 4, "Forgery and Counterfeiting": 3, "Fraud": 10, "Gambling - Total": 0, "Human Trafficking - Commercial Sex Acts": 1, "Human Trafficking - Involuntary Servitude": 0, "Larceny - Theft": 96, "Liquor Laws": 8, "Manslaughter by Negligence": 2, "Motor Vehicle Theft": 9, "Murder and Nonnegligent Manslaughter": 7, "Offenses Against the Family and Children": 1, "Prostitution and Commercialized Vice": 4, "Rape": 1, "Robbery": 3, "Simple Assault": 138, "Stolen Property: Buying, Receiving, Possessing": 2, "Suspicion": 0, "Vagrancy": 0, "Vandalism": 23, "Weapons: Carrying, Possessing, Etc.": 34, "Sex Offenses (Except Rape, and Prostitution and Commercialized Vice)": 2}]}